{
  "field": "target",
  "keywords": {
    "A食堂1楼大餐厅": {
      "position": "海馨楼",
      "name": "第1食堂"
    },
    "A食堂1楼小餐厅": {
      "position": "海馨楼",
      "name": "第3食堂"
    },
    "A食堂1楼清真餐厅": {
      "position": "海馨楼",
      "name": "第5食堂(清真)"
    },
    "A食堂2楼大餐厅": {
      "position": "海馨楼",
      "name": "第2食堂"
    },
    "A食堂2楼小餐厅": {
      "position": "海馨楼",
      "name": "第4食堂"
    },
    "B食堂1楼": {
      "position": "海琴楼",
      "name": "海琴1楼"
    },
    "B食堂2楼": {
      "position": "海琴楼",
      "name": "海琴1楼"
    },
    "C1大餐厅": {
      "position": "海联楼",
      "name": "海联1楼"
    },
    "C食堂2楼": {
      "position": "海联楼",
      "name": "海联2楼"
    }
  }
}